solvedac_community/__init__.py
solvedac_community/client.py
solvedac_community/HTTPClients/__init__.py
solvedac_community/HTTPClients/abstract_http_client.py
solvedac_community/HTTPClients/aiohttp_client.py
solvedac_community/HTTPClients/httpclient.py
solvedac_community/HTTPClients/httpx_client.py
solvedac_community/Schemas/__init__.py
solvedac_community/Schemas/Enums/__init__.py
solvedac_community/Schemas/Enums/badge_category.py
solvedac_community/Schemas/Enums/badge_tier.py
solvedac_community/Schemas/Enums/class_decoration.py
solvedac_community/Schemas/Enums/price_unit.py
solvedac_community/Schemas/Enums/problem_level.py
solvedac_community/Schemas/Enums/sort_direction.py
solvedac_community/Schemas/Enums/sort_type.py
solvedac_community/Schemas/Enums/user_tier.py
solvedac_community/Schemas/Models/__init__.py
solvedac_community/Schemas/Models/account_info.py
solvedac_community/Schemas/Models/author.py
solvedac_community/Schemas/Models/auto_complete_text.py
solvedac_community/Schemas/Models/auto_completion_data.py
solvedac_community/Schemas/Models/background.py
solvedac_community/Schemas/Models/badge.py
solvedac_community/Schemas/Models/coinshop_product.py
solvedac_community/Schemas/Models/emoticon_info.py
solvedac_community/Schemas/Models/item.py
solvedac_community/Schemas/Models/organization.py
solvedac_community/Schemas/Models/problem.py
solvedac_community/Schemas/Models/problem_level_data.py
solvedac_community/Schemas/Models/problem_search_data.py
solvedac_community/Schemas/Models/problem_stats.py
solvedac_community/Schemas/Models/problem_tag.py
solvedac_community/Schemas/Models/settings.py
solvedac_community/Schemas/Models/simplified_problem.py
solvedac_community/Schemas/Models/simplified_tag.py
solvedac_community/Schemas/Models/simplified_user.py
solvedac_community/Schemas/Models/solvedac_statistics.py
solvedac_community/Schemas/Models/tag_display_name.py
solvedac_community/Schemas/Models/tagged_problem.py
solvedac_community/Schemas/Models/user.py
solvedac_community-1.0.1.dist-info/METADATA
solvedac_community-1.0.1.dist-info/WHEEL
solvedac_community-1.0.1.dist-info/RECORD
