Metadata-Version: 2.1
Name: solvedac_community
Version: 1.0.1
Summary: An API Wrapper for SolvedAC API
Home-page: https://solvedac.github.io/unofficial-documentation/
License: MIT
Keywords: api-wrapper,solvedac,solvedac-api
Author: DevRuby
Author-email: hiveruby@gmail.com
Requires-Python: >=3.9,<4.0
Classifier: License :: OSI Approved :: MIT License
Classifier: Programming Language :: Python :: 3
Classifier: Programming Language :: Python :: 3.9
Classifier: Programming Language :: Python :: 3.10
Classifier: Programming Language :: Python :: 3.11
Classifier: Programming Language :: Python :: 3.12
Classifier: Topic :: Software Development :: Libraries
Classifier: Topic :: Software Development :: Libraries :: Python Modules
Project-URL: Repository, https://github.com/solvedac/python/
